rackio/__init__.py
rackio/_singleton.py
rackio/alarms.py
rackio/config.py
rackio/connection.py
rackio/controls.py
rackio/core.py
rackio/dbmodels.py
rackio/engine.py
rackio/events.py
rackio/exceptions.py
rackio/handlers.py
rackio/logger.py
rackio/models.py
rackio/state.py
rackio/status_code.py
rackio/system.py
rackio/utils.py
rackio/workers.py
rackio/api/__init__.py
rackio/api/alarms.py
rackio/api/auth.py
rackio/api/auth_hook.py
rackio/api/blobs.py
rackio/api/config.py
rackio/api/controls.py
rackio/api/core.py
rackio/api/events.py
rackio/api/groups.py
rackio/api/history.py
rackio/api/hook.py
rackio/api/logger.py
rackio/api/static.py
rackio/api/summary.py
rackio/api/tags.py
rackio/api/template.py
rackio/api/trends.py
rackio/api/waveforms.py
rackio/api/workers.py
rackio/dao/__init__.py
rackio/dao/alarms.py
rackio/dao/auth.py
rackio/dao/controls.py
rackio/dao/core.py
rackio/dao/events.py
rackio/dao/groups.py
rackio/dao/logger.py
rackio/dao/tags.py
rackio/logger/__init__.py
rackio/logger/data.py
rackio/logger/engine.py
rackio/logger/logdict.py
rackio/logger/query.py
rackio/management/__init__.py
rackio/management/utilities.py
rackio/managers/__init__.py
rackio/managers/alarms.py
rackio/managers/api.py
rackio/managers/auth.py
rackio/managers/controls.py
rackio/managers/functions.py
rackio/managers/logger.py
rackio/managers/state.py
rackio/utils/__init__.py
rackio/utils/auth.py
rackio/utils/database.py
rackio/utils/dir.py
rackio/utils/inspect.py
rackio/utils/observer.py
rackio/utils/other.py
rackio/web/__init__.py
rackio/web/render.py
rackio/web/resources.py
rackio/web/static.py
rackio/web/utils.py
rackio/workers/__init__.py
rackio/workers/alarms.py
rackio/workers/api.py
rackio/workers/continuos.py
rackio/workers/controls.py
rackio/workers/functions.py
rackio/workers/handlers.py
rackio/workers/logger.py
rackio/workers/state.py
rackio/workers/worker.py
Rackio-1.0.3.dist-info/LICENSE
Rackio-1.0.3.dist-info/METADATA
Rackio-1.0.3.dist-info/WHEEL
Rackio-1.0.3.dist-info/top_level.txt
Rackio-1.0.3.dist-info/RECORD
