Metadata-Version: 2.1
Name: Rackio
Version: 1.0.3
Summary: A modern Python Framework for microboard automation and control applications development
Home-page: https://github.com/rack-io/rackio-framework
Author: Nelson Carrasquel
Author-email: rackio.framework@outlook.com
License: MIT
Platform: UNKNOWN
Classifier: Programming Language :: Python :: 3
Classifier: License :: OSI Approved :: MIT License
Classifier: Operating System :: OS Independent
Requires-Dist: falcon
Requires-Dist: falcon-multipart
Requires-Dist: falcon-auth
Requires-Dist: falcon-cors
Requires-Dist: pyBigParser
Requires-Dist: peewee
Requires-Dist: python-statemachine
Requires-Dist: APScheduler
Requires-Dist: waitress
Requires-Dist: Jinja2
Requires-Dist: PyYAML
Requires-Dist: psycopg2
